d3dtools/__init__.py
d3dtools/describe.py
d3dtools/evaluate.py
d3dtools/evaluate_sensor.py
d3dtools/getfacez.py
d3dtools/ncrain.py
d3dtools/sensor.py
d3dtools/shp2ldb.py
d3dtools/shp2pli.py
d3dtools/shp2pliz.py
d3dtools/shp2pol.py
d3dtools/shp2xyz.py
d3dtools/shpbc2pli.py
d3dtools/shpblock2pol.py
d3dtools/shpdike2pliz.py
d3dtools/snorain.py
d3dtools/utils.py
d3dtools/tests/__init__.py
d3dtools/tests/test_sensor.py
d3dtools-0.15.2.dist-info/licenses/LICENSE
d3dtools-0.15.2.dist-info/METADATA
d3dtools-0.15.2.dist-info/WHEEL
d3dtools-0.15.2.dist-info/entry_points.txt
d3dtools-0.15.2.dist-info/top_level.txt
d3dtools-0.15.2.dist-info/RECORD
